{"_type":"export","__export_format":4,"__export_date":"2022-05-18T00:33:44.816Z","__export_source":"insomnia.desktop.app:v2022.3.0","resources":[{"_id":"req_5010271791e7446d8e4e2d60ed41a093","parentId":"fld_89d578124bd64705b0bb98b106301f7b","modified":1652829942289,"created":1652828290842,"url":"http://localhost:3030/msg/user/b","name":"CreateMsg","description":"","method":"POST","body":{"mimeType":"application/json","text":"{\n\t\"destinatario\": \"thiago32\",\n\t\"assunto\": \"Test 1\",\n\t\"mensagem\": \"olha essa msg\"\n}"},"parameters":[],"headers":[{"name":"Content-Type","value":"application/json","id":"pair_f6c6ee3900684eb294403c7821c045e3"}],"authentication":{},"metaSortKey":-1652828290842,"isPrivate":false,"settingStoreCookies":true,"settingSendCookies":true,"settingDisableRenderRequestBody":false,"settingEncodeUrl":true,"settingRebuildPath":true,"settingFollowRedirects":"global","_type":"request"},{"_id":"fld_89d578124bd64705b0bb98b106301f7b","parentId":"wrk_aa132522b6ba4e2eb6ef6e294cf41764","modified":1652828266635,"created":1652828266635,"name":"mensagem","description":"","environment":{},"environmentPropertyOrder":null,"metaSortKey":-1652828266635,"_type":"request_group"},{"_id":"wrk_aa132522b6ba4e2eb6ef6e294cf41764","parentId":null,"modified":1652747323373,"created":1652747323373,"name":"mensagemMail","description":"","scope":"collection","_type":"workspace"},{"_id":"req_4acf7a438a864a19bbc2374b6f22b208","parentId":"fld_89d578124bd64705b0bb98b106301f7b","modified":1652829950499,"created":1652829387354,"url":"http://localhost:3030/msgs","name":"FindAllMsgs","description":"","method":"GET","body":{},"parameters":[],"headers":[],"authentication":{},"metaSortKey":-1652828290792,"isPrivate":false,"settingStoreCookies":true,"settingSendCookies":true,"settingDisableRenderRequestBody":false,"settingEncodeUrl":true,"settingRebuildPath":true,"settingFollowRedirects":"global","_type":"request"},{"_id":"req_b34cb1e7aa544877b3b3543f0e1a9f1a","parentId":"fld_89d578124bd64705b0bb98b106301f7b","modified":1652830209524,"created":1652829767794,"url":"http://localhost:3030/msgs/user/bigue","name":"FindMsgs","description":"","method":"GET","body":{},"parameters":[],"headers":[],"authentication":{},"metaSortKey":-1652787835542.5,"isPrivate":false,"settingStoreCookies":true,"settingSendCookies":true,"settingDisableRenderRequestBody":false,"settingEncodeUrl":true,"settingRebuildPath":true,"settingFollowRedirects":"global","_type":"request"},{"_id":"req_bc9ca228abbb48a49a31902dba2e8ab7","parentId":"fld_89d578124bd64705b0bb98b106301f7b","modified":1652831515430,"created":1652830368279,"url":"http://localhost:3030/msg/1","name":"DeleteMsg","description":"","method":"DELETE","body":{},"parameters":[],"headers":[],"authentication":{},"metaSortKey":-1652787835492.5,"isPrivate":false,"settingStoreCookies":true,"settingSendCookies":true,"settingDisableRenderRequestBody":false,"settingEncodeUrl":true,"settingRebuildPath":true,"settingFollowRedirects":"global","_type":"request"},{"_id":"req_398c8a48c343404486d8fa8baef6c900","parentId":"fld_37c10659fe9c4fcfa645525d597d0166","modified":1652828701463,"created":1652747380293,"url":"http://localhost:3030/user","name":"CreateUser","description":"","method":"POST","body":{"mimeType":"application/json","text":"{\n\t\"usuario\": \"Thiago32\",\n\t\"nome\": \"Thiago Pereira\",\n\t\"senha\": \"123456\"\n}"},"parameters":[],"headers":[{"name":"Content-Type","value":"application/json","id":"pair_91003a051b22440ab354c795328ead56"}],"authentication":{},"metaSortKey":-1652747380293,"isPrivate":false,"settingStoreCookies":true,"settingSendCookies":true,"settingDisableRenderRequestBody":false,"settingEncodeUrl":true,"settingRebuildPath":true,"settingFollowRedirects":"global","_type":"request"},{"_id":"fld_37c10659fe9c4fcfa645525d597d0166","parentId":"wrk_aa132522b6ba4e2eb6ef6e294cf41764","modified":1652747332706,"created":1652747332706,"name":"user","description":"","environment":{},"environmentPropertyOrder":null,"metaSortKey":-1652747332706,"_type":"request_group"},{"_id":"req_90678e5649204c88983b57ff643b7530","parentId":"fld_37c10659fe9c4fcfa645525d597d0166","modified":1652825893648,"created":1652748117478,"url":"http://localhost:3030/users/","name":"FindAllUsers","description":"","method":"GET","body":{},"parameters":[],"headers":[],"authentication":{},"metaSortKey":-1652747380243,"isPrivate":false,"settingStoreCookies":true,"settingSendCookies":true,"settingDisableRenderRequestBody":false,"settingEncodeUrl":true,"settingRebuildPath":true,"settingFollowRedirects":"global","_type":"request"},{"_id":"req_eb1a18251d3b46f290edf0268767ddea","parentId":"fld_37c10659fe9c4fcfa645525d597d0166","modified":1652833915901,"created":1652832843058,"url":"http://localhost:3030/user/login","name":"LoginUser","description":"","method":"POST","body":{"mimeType":"application/json","text":"{\n\t\"usuario\": \"Thiago32\",\n\t\"senha\": \"123456\"\n}"},"parameters":[],"headers":[{"name":"Content-Type","value":"application/json","id":"pair_fb744c6d82c644a3a316d520bd9c5aa5"}],"authentication":{},"metaSortKey":-1652747380218,"isPrivate":false,"settingStoreCookies":true,"settingSendCookies":true,"settingDisableRenderRequestBody":false,"settingEncodeUrl":true,"settingRebuildPath":true,"settingFollowRedirects":"global","_type":"request"},{"_id":"req_51ac0eea2b0f42818006786a6c034ef7","parentId":"fld_37c10659fe9c4fcfa645525d597d0166","modified":1652825939562,"created":1652748317905,"url":"http://localhost:3030/user/thiago32","name":"FindUser","description":"","method":"GET","body":{},"parameters":[],"headers":[],"authentication":{},"metaSortKey":-1652747380193,"isPrivate":false,"settingStoreCookies":true,"settingSendCookies":true,"settingDisableRenderRequestBody":false,"settingEncodeUrl":true,"settingRebuildPath":true,"settingFollowRedirects":"global","_type":"request"},{"_id":"req_effb6f6362ba4c428355e924faa962ab","parentId":"fld_37c10659fe9c4fcfa645525d597d0166","modified":1652829377698,"created":1652748678949,"url":"http://localhost:3030/user/thiago32","name":"UpdateUser","description":"","method":"PUT","body":{"mimeType":"application/json","text":"{\n\t\"nome\": \"Thiago3\"\n}"},"parameters":[],"headers":[{"name":"Content-Type","value":"application/json","id":"pair_280f6e1233f642dba9464359d079eafd"}],"authentication":{},"metaSortKey":-1652747380143,"isPrivate":false,"settingStoreCookies":true,"settingSendCookies":true,"settingDisableRenderRequestBody":false,"settingEncodeUrl":true,"settingRebuildPath":true,"settingFollowRedirects":"global","_type":"request"},{"_id":"req_f4085578d2974f7aa789df3acb4f84ce","parentId":"fld_37c10659fe9c4fcfa645525d597d0166","modified":1652830364514,"created":1652749023683,"url":"","name":"DeleteUser","description":"","method":"DELETE","body":{},"parameters":[],"headers":[],"authentication":{},"metaSortKey":-1652747380093,"isPrivate":false,"settingStoreCookies":true,"settingSendCookies":true,"settingDisableRenderRequestBody":false,"settingEncodeUrl":true,"settingRebuildPath":true,"settingFollowRedirects":"global","_type":"request"},{"_id":"env_095c72eed8af14ba59a404ad281e144278afbda2","parentId":"wrk_aa132522b6ba4e2eb6ef6e294cf41764","modified":1652747323380,"created":1652747323380,"name":"Base Environment","data":{},"dataPropertyOrder":null,"color":null,"isPrivate":false,"metaSortKey":1652747323380,"_type":"environment"},{"_id":"jar_095c72eed8af14ba59a404ad281e144278afbda2","parentId":"wrk_aa132522b6ba4e2eb6ef6e294cf41764","modified":1652747323383,"created":1652747323383,"name":"Default Jar","cookies":[],"_type":"cookie_jar"},{"_id":"spc_bd4081722aea4b8fa7868f4ecbcc8aa8","parentId":"wrk_aa132522b6ba4e2eb6ef6e294cf41764","modified":1652747323374,"created":1652747323374,"fileName":"mensagemMail","contents":"","contentType":"yaml","_type":"api_spec"}]}